setup.py
src/test_nothing/__init__.py
src/test_nothing.egg-info/PKG-INFO
src/test_nothing.egg-info/SOURCES.txt
src/test_nothing.egg-info/dependency_links.txt
src/test_nothing.egg-info/top_level.txt