Metadata-Version: 1.0
Name: test-nothing
Version: 0.0.0
Summary: Just an empty project to test pypi registering
Home-page: UNKNOWN
Author: Pierre-Francois Carpentier
Author-email: carpentier.pf [ at ] gmail.com
License: WTFPL
Platform: UNKNOWN
